{"is_source_file": false, "format": "", "description": "", "external_files": [], "external_methods": [], "published": [], "classes": [], "methods": [], "calls": [], "search-terms": [], "state": 2, "file_id": 13, "knowledge_revision": 28, "git_revision": "48d91331f1f0adb3f904a6b2d521c455ad30622e", "hash": "b0e227735188cf54e963b9d88bf2c824", "format-version": 4, "code-base-name": "frontend_chatbot_ui", "filename": "frontend_chatbot_ui/src/App.css", "revision_history": [{"28": "48d91331f1f0adb3f904a6b2d521c455ad30622e"}]}